MANIFEST.in
README.rst
setup.py
version.txt
micral_classify_core/CrystNet1.2.hdf5
micral_classify_core/__init__.py
micral_classify_core/micral_classify_core.py
micral_classify_core/version.txt
micral_classify_core.egg-info/PKG-INFO
micral_classify_core.egg-info/SOURCES.txt
micral_classify_core.egg-info/dependency_links.txt
micral_classify_core.egg-info/not-zip-safe
micral_classify_core.egg-info/requires.txt
micral_classify_core.egg-info/top_level.txt