Metadata-Version: 1.0
Name: micral-classify-core
Version: 2.0
Summary: Classification tool between martensite, spheroidite and pearlite
Home-page: UNKNOWN
Author: Yann LEROY
Author-email: yann.leroy102@orange.fr
License: MIT
Platform: UNKNOWN
